{
  "interface_language": "中文",
  "tray_mode": false,
  "x264_priority": "正常",
  "x264_threads": 0,
  "x264_command": "",
  "default_player": "",
  "preferred_device": "优先 GPU",
  "enable_drag_drop": true,
  "confirm_overwrite": true,
  "auto_open_output": false,
  "advanced_encoders": false,
  "tab_order": [
    "视频",
    "变形",
    "封装",
    "字幕",
    "音频",
    "常用",
    "复古",
    "Lut调色",
    "批量压缩",
    "MediaInfo",
    "任务管理"
  ],
  "audio_output_mode": "自定义",
  "audio_output_dir": "Z:\\PROG视频高性能压缩器\\output\\audio",
  "audio_overwrite_source": false,
  "video_settings": {
    "encoder_name": "GPU H.265 / HEVC (hevc_nvenc)",
    "advanced_encoders": false,
    "preset_name": "高速",
    "resolution_name": "保持原分辨率",
    "sharpen_name": "关闭",
    "custom_width": 1920,
    "custom_height": 1080,
    "quality_mode": "CRF / 恒定质量",
    "cq_value": 23,
    "bitrate": "",
    "custom_command": "-y -i \"{input}\" -c:v libx264 -crf 23 -c:a copy \"{output}\"",
    "audio_mode": "复制音频流",
    "audio_bitrate": "",
    "muxer_name": "MP4 (.mp4)",
    "create_thumbnail": true,
    "thumbnail_only_selected": false,
    "thumbnail_time": 1.0,
    "parallel_jobs": 2,
    "extra_ffmpeg_args": "",
    "use_lut": false,
    "lut_path": "",
    "file_conflict_action": "重命名"
  },
  "output_dir": "Z:\\PROG视频高性能压缩器\\output",
  "audio_encoder_name": "AAC (.m4a)",
  "audio_page_bitrate": "192k",
  "audio_sample_rate": "48000",
  "audio_channels": "2",
  "audio_normalize": false,
  "common_output_dir": "Z:\\PROG视频高性能压缩器\\output\\common",
  "common_trim_start": "00:00:00",
  "common_trim_end": "00:00:10",
  "common_trim_encoder": "CPU H.264 / AVC (libx264)",
  "common_trim_muxer": "MP4 (.mp4)",
  "subtitle_output_dir": "Z:\\PROG视频高性能压缩器\\output\\subtitles",
  "subtitle_output_format": "MKV (.mkv)",
  "anamorphic_output_dir": "Z:\\PROG视频高性能压缩器\\output\\anamorphic",
  "anamorphic_factor": "1.33",
  "anamorphic_mode": "保留反挤压宽画幅",
  "anamorphic_target_aspect": "2.39:1",
  "anamorphic_resolution": "保持反挤压尺寸",
  "anamorphic_encoder_name": "CPU H.264 / AVC (libx264)",
  "anamorphic_keep_audio": true,
  "anamorphic_auto_crop": false,
  "mux_output_dir": "Z:\\PROG视频高性能压缩器\\output\\mux",
  "mux_merge_name": "merged",
  "mux_merge_format": "MP4 (.mp4)",
  "mux_convert_format": "MP4 (.mp4)",
  "mux_audio_mode": "复制音频",
  "mux_audio_bitrate": "192k",
  "batch_input_dir": "",
  "batch_output_dir": "Z:\\PROG视频高性能压缩器\\output\\batch",
  "batch_preset_name": "网盘归档 H.265 1080p",
  "batch_keep_tree": true,
  "batch_include_audio": true,
  "batch_vertical_mode": false,
  "queue_parallel_jobs": 1,
  "retro_output_dir": "Z:\\PROG视频高性能压缩器\\output\\retro",
  "retro_format_name": "AVI - MPEG4 + MP3 (.avi)",
  "retro_resolution_name": "VCD 352x288",
  "retro_bitrate": "900k",
  "retro_audio_bitrate": "128k",
  "retro_deinterlace": true,
  "retro_denoise": true,
  "retro_remux_format": "MP4 (.mp4)",
  "retro_remux_audio": "复制音频",
  "screenshot_dir": "Z:\\PROG视频高性能压缩器\\output\\screenshots",
  "lut_page_video": "",
  "lut_page_folder": "",
  "lut_page_output": "Z:\\PROG视频高性能压缩器\\output\\lut_previews",
  "lut_page_time": 1.0,
  "main_window_geometry": "1320x1002+962+511",
  "main_window_state": "normal"
}